sirji_agents/__init__.py
sirji_agents/decorators.py
sirji_agents/llm/__init__.py
sirji_agents/llm/orchestrator.py
sirji_agents/llm/generic/__init__.py
sirji_agents/llm/generic/infer.py
sirji_agents/llm/generic/system_prompts/__init__.py
sirji_agents/llm/generic/system_prompts/anthropic.py
sirji_agents/llm/generic/system_prompts/default.py
sirji_agents/llm/generic/system_prompts/factory.py
sirji_agents/llm/model_providers/__init__.py
sirji_agents/llm/model_providers/anthropic.py
sirji_agents/llm/model_providers/base.py
sirji_agents/llm/model_providers/deepseek.py
sirji_agents/llm/model_providers/factory.py
sirji_agents/llm/model_providers/openai.py
sirji_agents/researcher/__init__.py
sirji_agents/researcher/researcher.py
sirji_agents/researcher/cleanup/__init__.py
sirji_agents/researcher/cleanup/base.py
sirji_agents/researcher/cleanup/factory.py
sirji_agents/researcher/cleanup/openai_cleanup.py
sirji_agents/researcher/embeddings/__init__.py
sirji_agents/researcher/embeddings/base.py
sirji_agents/researcher/embeddings/factory.py
sirji_agents/researcher/embeddings/openai_assistant.py
sirji_agents/researcher/inferer/__init__.py
sirji_agents/researcher/inferer/base.py
sirji_agents/researcher/inferer/factory.py
sirji_agents/researcher/inferer/openai_assistant.py
sirji_agents-0.0.51.dist-info/LICENSE
sirji_agents-0.0.51.dist-info/METADATA
sirji_agents-0.0.51.dist-info/WHEEL
sirji_agents-0.0.51.dist-info/top_level.txt
sirji_agents-0.0.51.dist-info/RECORD
