Metadata-Version: 2.1
Name: sirji-agents
Version: 0.0.51
Summary: Orchestrator, Generic Agent, and Research Agent components of the Sirji AI agentic framework.
Home-page: https://github.com/sirji-ai/sirji
Author: Sirji
License: MIT
Requires-Python: >=3.6
License-File: LICENSE
Requires-Dist: sirji-messages==0.0.34
Requires-Dist: sirji-tools==0.0.16
Requires-Dist: openai==1.35.7
Requires-Dist: anthropic==0.29.0
Requires-Dist: requests==2.31.0
Requires-Dist: httpx==0.27.0
